app/__init__.py
app/auth.py
app/config.py
app/database.py
app/models.py
app/routes.py
app/schemas.py
app/services.py
todo_list_app_mar_pal-0.1.1.dist-info/METADATA
todo_list_app_mar_pal-0.1.1.dist-info/WHEEL
todo_list_app_mar_pal-0.1.1.dist-info/entry_points.txt
todo_list_app_mar_pal-0.1.1.dist-info/top_level.txt
todo_list_app_mar_pal-0.1.1.dist-info/RECORD
