Metadata-Version: 2.2
Name: todo_list_app_Mar_Pal
Version: 0.1.1
Summary: A todo list app
Home-page: https://github.com/mp9466/todo-list-app
Author: Marko Palinec
Author-email: marko.palin@gmail.com
Classifier: Programming Language :: Python :: 3
Classifier: License :: OSI Approved :: MIT License
Classifier: Operating System :: OS Independent
Requires-Python: >=3.6
Requires-Dist: fastapi
Requires-Dist: uvicorn
Requires-Dist: sqlalchemy
Requires-Dist: pydantic
Requires-Dist: pydantic-settings
Requires-Dist: psycopg2-binary
Requires-Dist: alembic
Requires-Dist: python-dotenv
Requires-Dist: pytest
Requires-Dist: httpx
Requires-Dist: pytest-asyncio
Dynamic: author
Dynamic: author-email
Dynamic: classifier
Dynamic: description
Dynamic: description-content-type
Dynamic: home-page
Dynamic: requires-dist
Dynamic: requires-python
Dynamic: summary
